zensols/hostcon/__init__.py
zensols/hostcon/cli.py
zensols/hostcon/config.py
zensols/hostcon/connector.py
zensols.hostcon-0.5.0.dist-info/METADATA
zensols.hostcon-0.5.0.dist-info/RECORD
zensols.hostcon-0.5.0.dist-info/WHEEL
zensols.hostcon-0.5.0.dist-info/entry_points.txt
zensols.hostcon-0.5.0.dist-info/top_level.txt
