Metadata-Version: 2.1
Name: zensols.hostcon
Version: 0.5.0
Summary: Load servers from a file, list, login, and SSH mount
Home-page: https://github.com/plandes/hostcon
Author: Paul Landes
Author-email: landes@mailc.net
License: UNKNOWN
Download-URL: https://github.com/plandes/hostcon/releases/download/v0.5.0/zensols.hostcon-0.5.0-py3-none-any.whl
Keywords: tooling
Platform: UNKNOWN
Requires-Dist: zensols.actioncli (>=1.0.9)
